curriculum_guard/__init__.py
curriculum_guard/api.py
curriculum_guard/bucketer/__init__.py
curriculum_guard/bucketer/difficulty_bucketer.py
curriculum_guard/core/__init__.py
curriculum_guard/core/guard.py
curriculum_guard/core/state.py
curriculum_guard/engine/__init__.py
curriculum_guard/engine/engine.py
curriculum_guard/policy/__init__.py
curriculum_guard/policy/curriculum_policy.py
curriculum_guard/profiler/__init__.py
curriculum_guard/profiler/sample_profiler.py
curriculum_guard/safety/__init__.py
curriculum_guard/safety/safety_controller.py
curriculum_guard/sampler/__init__.py
curriculum_guard/sampler/adaptive_sampler.py
curriculumguard-0.2.0.dist-info/licenses/LICENSE
curriculumguard-0.2.0.dist-info/METADATA
curriculumguard-0.2.0.dist-info/WHEEL
curriculumguard-0.2.0.dist-info/top_level.txt
curriculumguard-0.2.0.dist-info/RECORD
