Metadata-Version: 2.4
Name: curriculumguard
Version: 0.2.0
Summary: Training-time adaptive data curriculum for PyTorch with safety guards
Author: Shaurya Jain
License: MIT
License-File: LICENSE
Requires-Dist: torch
Requires-Dist: numpy
Dynamic: license-file
